foliant/__init__.py
foliant/backends/__init__.py
foliant/backends/base.py
foliant/backends/pre.py
foliant/cli/__init__.py
foliant/cli/base.py
foliant/cli/make.py
foliant/config/__init__.py
foliant/config/base.py
foliant/config/env.py
foliant/config/include.py
foliant/config/path.py
foliant/preprocessors/__init__.py
foliant/preprocessors/_unescape.py
foliant/preprocessors/base.py
foliant/utils.py
foliant-1.0.13.dist-info/entry_points.txt
foliant-1.0.13.dist-info/LICENSE
foliant-1.0.13.dist-info/WHEEL
foliant-1.0.13.dist-info/METADATA
foliant-1.0.13.dist-info/RECORD
