Metadata-Version: 2.1
Name: foliant
Version: 1.0.13
Summary: Modular, Markdown-based documentation generator that makes pdf, docx, html, and more.
Home-page: https://foliant-docs.github.io/docs/
License: MIT
Keywords: documentation,markdown,html,docx,pdf
Author: Konstantin Molchanov
Author-email: moigagoo@live.com
Requires-Python: >=3.6,<4.0
Classifier: License :: OSI Approved :: MIT License
Classifier: Programming Language :: Python :: 3
Classifier: Programming Language :: Python :: 3.10
Classifier: Programming Language :: Python :: 3.6
Classifier: Programming Language :: Python :: 3.7
Classifier: Programming Language :: Python :: 3.8
Classifier: Programming Language :: Python :: 3.9
Requires-Dist: cliar (>=1.3.2,<2.0.0)
Requires-Dist: prompt_toolkit (>=2.0,<3.0)
Requires-Dist: pyyaml (>=5.1.1,<6.0.0)
Project-URL: Documentation, https://foliant-docs.github.io/docs/
Project-URL: Repository, https://github.com/foliant-docs/foliant
